heat_package/__init__.py
heat_package/index.py
mpg_heatindex-0.2.3.dist-info/LICENSE
mpg_heatindex-0.2.3.dist-info/METADATA
mpg_heatindex-0.2.3.dist-info/WHEEL
mpg_heatindex-0.2.3.dist-info/top_level.txt
mpg_heatindex-0.2.3.dist-info/RECORD
